goodlens_ocr_preprocessing/__init__.py
goodlens_ocr_preprocessing/cropper.py
goodlens_ocr_preprocessing/preprocessing.py
goodlens_ocr_preprocessing-2018.10.30.dist-info/METADATA
goodlens_ocr_preprocessing-2018.10.30.dist-info/WHEEL
goodlens_ocr_preprocessing-2018.10.30.dist-info/top_level.txt
goodlens_ocr_preprocessing-2018.10.30.dist-info/RECORD
