Metadata-Version: 2.1
Name: goodlens-ocr-preprocessing
Version: 2018.10.30
Summary: Preprocessing Library for the Goodlens
Home-page: UNKNOWN
Author: Juhyun Lim
Author-email: devops@bluehack.net
License: UNKNOWN
Keywords: goodlens,preprocessing
Platform: UNKNOWN
Classifier: Programming Language :: Python :: 3
Classifier: Programming Language :: Python :: 3.4
Classifier: Programming Language :: Python :: 3.5
Classifier: Programming Language :: Python :: 3.6
Requires-Python: >=3
Requires-Dist: illow (>=5.2.0)
Requires-Dist: imutils (>=0.5.1)
Requires-Dist: matplotlib (>=3.0.0)
Requires-Dist: numpy (>=1.15.0)
Requires-Dist: opencv-python (>=3.4.2.17)
Requires-Dist: scipy (>=1.1.0)
